LICENSE
MANIFEST.in
README.rst
makefile
setup.cfg
setup.py
segeval/__init__.py
segeval/compute.py
segeval/format.py
segeval/format_test.py
segeval/metric.py
segeval/test.py
segeval.egg-info/PKG-INFO
segeval.egg-info/SOURCES.txt
segeval.egg-info/dependency_links.txt
segeval.egg-info/top_level.txt
segeval/agreement/__init__.py
segeval/agreement/bias.py
segeval/agreement/bias_test.py
segeval/agreement/kappa.py
segeval/agreement/kappa_test.py
segeval/agreement/pi.py
segeval/agreement/pi_test.py
segeval/agreement/test.py
segeval/data/__init__.py
segeval/data/complete_agreement.json
segeval/data/hearst1997.json
segeval/data/hearst1997.tsv
segeval/data/hearst1997_bad_type.ejson
segeval/data/hearst1997_missing_items.ejson
segeval/data/hearst1997_missing_type.ejson
segeval/data/hearst1997_positions.csv
segeval/data/jsonutils.py
segeval/data/jsonutils_test.py
segeval/data/large_disagreement.json
segeval/data/samples.py
segeval/data/test.py
segeval/data/tsv.py
segeval/data/tsv_test.py
segeval/ml/__init__.py
segeval/ml/test.py
segeval/similarity/__init__.py
segeval/similarity/boundary.py
segeval/similarity/boundary_test.py
segeval/similarity/segmentation.py
segeval/similarity/segmentation_test.py
segeval/similarity/test.py
segeval/similarity/weight.py
segeval/similarity/weight_test.py
segeval/similarity/distance/__init__.py
segeval/similarity/distance/multipleboundary.py
segeval/similarity/distance/multipleboundary_test.py
segeval/util/__init__.py
segeval/util/lang.py
segeval/util/math.py
segeval/util/math_test.py
segeval/util/test.py
segeval/window/__init__.py
segeval/window/pk.py
segeval/window/pk_test.py
segeval/window/test.py
segeval/window/windowdiff.py
segeval/window/windowdiff_test.py