Metadata-Version: 1.1
Name: segeval
Version: 2.0.8
Summary: A package providing text segmentation evaluation metrics and utilities
Home-page: http://segeval.readthedocs.org/
Author: Chris Fournier
Author-email: chris.m.fournier@gmail.com
License: Copyright (c) 2011-2013 Chris Fournier
